Workbook
Name Aporte: Sheet2!$D$17
Name Patrimonio: Sheet2!$D$20
Name Qtd_anos: Sheet2!$D$18
Name Rendimento_Carteira: Sheet2!$D$13
Name Salario: Sheet2!$D$12
Name Sugestao_investimento: Sheet2!$D$14
Name Taxa_mensal: Sheet2!$D$19

Sheet Sheet1
A1: Tabela de apoio
A2: CHAVE | B2: PERFIL | C2: TIPO DE FII | D2: %
A3: =B3&"-"&C3 -> CONSERVADOR-PAPEL | B3: CONSERVADOR | C3: PAPEL | D3: 0.35
A4: =B4&"-"&C4 -> CONSERVADOR-TIJOLO | B4: CONSERVADOR | C4: TIJOLO | D4: 0.45 | G4: %
A5: =B5&"-"&C5 -> CONSERVADOR-HIBRIDOS | B5: CONSERVADOR | C5: HIBRIDOS | D5: 0.15 | F5: MODERADO-TIJOLO | G5: =VLOOKUP(F5,$A:$D,4,FALSE) -> 0.35
A6: =B6&"-"&C6 -> CONSERVADOR-FOFs | B6: CONSERVADOR | C6: FOFs | D6: 0.05
A7: =B7&"-"&C7 -> CONSERVADOR-DESENVOLVIMENTO | B7: CONSERVADOR | C7: DESENVOLVIMENTO | D7: 0
A8: =B8&"-"&C8 -> CONSERVADOR-HOTELARIAS | B8: CONSERVADOR | C8: HOTELARIAS | D8: 0
A9: =B9&"-"&C9 -> MODERADO-PAPEL | B9: MODERADO | C9: PAPEL | D9: 0.35 | K9: )
A10: =B10&"-"&C10 -> MODERADO-TIJOLO | B10: MODERADO | C10: TIJOLO | D10: 0.35
A11: =B11&"-"&C11 -> MODERADO-HIBRIDOS | B11: MODERADO | C11: HIBRIDOS | D11: 0.05
A12: =B12&"-"&C12 -> MODERADO-FOFs | B12: MODERADO | C12: FOFs | D12: 0.05
A13: =B13&"-"&C13 -> MODERADO-DESENVOLVIMENTO | B13: MODERADO | C13: DESENVOLVIMENTO | D13: 0.1
A14: =B14&"-"&C14 -> MODERADO-HOTELARIAS | B14: MODERADO | C14: HOTELARIAS | D14: 0.1
A15: =B15&"-"&C15 -> AGRESSIVO-PAPEL | B15: AGRESSIVO | C15: PAPEL | D15: 0.4
A16: =B16&"-"&C16 -> AGRESSIVO-TIJOLO | B16: AGRESSIVO | C16: TIJOLO | D16: 0.2
A17: =B17&"-"&C17 -> AGRESSIVO-HIBRIDOS | B17: AGRESSIVO | C17: HIBRIDOS | D17: 0.05
A18: =B18&"-"&C18 -> AGRESSIVO-FOFs | B18: AGRESSIVO | C18: FOFs | D18: 0.05
A19: =B19&"-"&C19 -> AGRESSIVO-DESENVOLVIMENTO | B19: AGRESSIVO | C19: DESENVOLVIMENTO | D19: 0.2
A20: =B20&"-"&C20 -> AGRESSIVO-HOTELARIAS | B20: AGRESSIVO | C20: HOTELARIAS | D20: 0.1

Sheet Sheet2
B11: CONFIGURACOES
B12: Salario | D12: 10000
B13: Rendimento Carteira | D13: 0.01
B14: Sugestao de Investimento | D14: =D12*30% -> 3000
B16: INVESTIMENTO MENSAL
B17: Quanto investir por mes? | D17: 3000
B18: Por quantos anos? | D18: 10
B19: Taxa de rendimento mensal? | D19: 0.01079
B20: quanto de patrimonio acumulado terei? | D20: =FV(Taxa_mensal,Qtd_anos*12,Aporte*-1) -> 729852.64
B21: quanto dividendos mensais? | D21: =Patrimonio*Rendimento_Carteira -> 7298.5264
B23: Cenarios | D23: Dividendos
A24: 2 | B24: Quanto em 2 Anos? | C24: =FV($D$19,$A24*12,$D$17*-1) -> 81682.882 | D24: =C24*Rendimento_Carteira -> 816.82882
A25: 5 | B25: Quanto em 5 Anos? | C25: =FV($D$19,$A25*12,$D$17*-1) -> 251330.74 | D25: =C25*Rendimento_Carteira -> 2513.3074
A26: 10 | B26: Quanto em 10 Anos? | C26: =FV($D$19,$A26*12,$D$17*-1) -> 729852.64 | D26: =C26*Rendimento_Carteira -> 7298.5264
A27: 20 | B27: Quanto em 20 Anos? | C27: =FV($D$19,$A27*12,$D$17*-1) -> 3375595.2 | D27: =C27*Rendimento_Carteira -> 33755.952
A28: 30 | B28: Quanto em 30 Anos? | C28: =FV($D$19,$A28*12,$D$17*-1) -> 12966509 | D28: =C28*Rendimento_Carteira -> 129665.09
B31: PERFIL | C31: CONSERVADOR
B32: VALOR A SER INVESTIDO POR MES | C32: =Aporte -> 3000
B34: TIPO DE FII | C34: Perncetual sugerido | D34: Valores
B35: PAPEL | C35: =VLOOKUP($C$31&"-"&B35,Sheet1!$A:$D,4,FALSE) -> 0.35 | D35: =C35*$C$32 -> 1050
B36: TIJOLO | C36: =VLOOKUP($C$31&"-"&B36,Sheet1!$A:$D,4,FALSE) -> 0.45 | D36: =C36*$C$32 -> 1350
B37: HIBRIDOS | C37: =VLOOKUP($C$31&"-"&B37,Sheet1!$A:$D,4,FALSE) -> 0.15 | D37: =C37*$C$32 -> 450
B38: FOFs | C38: =VLOOKUP($C$31&"-"&B38,Sheet1!$A:$D,4,FALSE) -> 0.05 | D38: =C38*$C$32 -> 150
B39: DESENVOLVIMENTO | C39: =VLOOKUP($C$31&"-"&B39,Sheet1!$A:$D,4,FALSE) -> 0 | D39: =C39*$C$32 -> 0
B40: HOTELARIAS | C40: =VLOOKUP($C$31&"-"&B40,Sheet1!$A:$D,4,FALSE) -> 0 | D40: =C40*$C$32 -> 0
D41: =SUM(D35:D40) -> 3000
